jisuanqi.py
jisuanqi-6.0.0.dist-info/METADATA
jisuanqi-6.0.0.dist-info/WHEEL
jisuanqi-6.0.0.dist-info/top_level.txt
jisuanqi-6.0.0.dist-info/RECORD
