Metadata-Version: 2.1
Name: jisuanqi
Version: 6.0.0
Summary: 简单计算器(Calculator)(喜欢关注:python学霸微信公众号)
Home-page: UNKNOWN
Author: Python学霸
Author-email: python@xueba.com
License: UNKNOWN
Platform: UNKNOWN
